leeteasy/__init__.py
leeteasy/__main__.py
leeteasy/constant.py
leeteasy/assets/__init__.py
leeteasy/assets/leetcoin.png
leeteasy/models/__init__.py
leeteasy/models/challenge.py
leeteasy/services/__init__.py
leeteasy/services/notification_service.py
leeteasy/services/request_handler.py
leeteasy/services/request_parser.py
leeteasy/utils/__init__.py
leeteasy/utils/validatiors.py
leeteasy-1.2.0.dist-info/LICENSE
leeteasy-1.2.0.dist-info/METADATA
leeteasy-1.2.0.dist-info/WHEEL
leeteasy-1.2.0.dist-info/entry_points.txt
leeteasy-1.2.0.dist-info/top_level.txt
leeteasy-1.2.0.dist-info/RECORD
