Metadata-Version: 2.1
Name: leeteasy
Version: 1.2.0
Summary: Desktop notification of easy daily challenge of leetcode.
Home-page: https://github.com/sudiptob2/leet-easy
Author: Sudipto Baral
Author-email: sudiptobaral.me@gmail.com
Classifier: Development Status :: 3 - Alpha
Classifier: Environment :: Console
Classifier: Intended Audience :: Information Technology
Classifier: License :: OSI Approved :: GNU General Public License v3 (GPLv3)
Classifier: Operating System :: MacOS
Classifier: Operating System :: Microsoft
Classifier: Operating System :: POSIX :: Linux
Classifier: Programming Language :: Python :: 3.8
Classifier: Topic :: Software Development
Classifier: Topic :: Terminals
Requires-Python: >=3.8
License-File: LICENSE
Requires-Dist: click (==8.1.3)
Requires-Dist: idna (==3.4)
Requires-Dist: notify-py (==0.3.3)
Requires-Dist: requests (==2.28.1)
Requires-Dist: schedule (==1.1.0)
